sirdjango_takeflight
