Metadata-Version: 1.1
Name: sirdjango-takeflight
Version: 0.1.4
Summary: Reusable Sir Trevor blocks
Home-page: https://bitbucket.org/takeflight/sirdjango_takeflight/
Author: Takeflight
Author-email: admin@takeflight.com.au
License: BSD License
Platform: UNKNOWN
Classifier: Environment :: Web Environment
Classifier: Intended Audience :: Developers
Classifier: Operating System :: OS Independent
Classifier: Programming Language :: Python
Classifier: Framework :: Django
Classifier: License :: OSI Approved :: BSD License
